mir/cp/__init__.py
mir.cp-1.0.0.dist-info/DESCRIPTION.rst
mir.cp-1.0.0.dist-info/METADATA
mir.cp-1.0.0.dist-info/RECORD
mir.cp-1.0.0.dist-info/WHEEL
mir.cp-1.0.0.dist-info/metadata.json
mir.cp-1.0.0.dist-info/top_level.txt
