Metadata-Version: 2.0
Name: mir.cp
Version: 1.0.0
Summary: Cached property implementation
Home-page: https://github.com/darkfeline/mir.cp
Author: Allen Li
Author-email: darkfeline@felesatra.moe
License: UNKNOWN
Platform: UNKNOWN
Classifier: Development Status :: 3 - Alpha
Classifier: Intended Audience :: Developers
Classifier: License :: OSI Approved :: Apache Software License
Classifier: Programming Language :: Python :: 3.6
